<?xml version="1.0" encoding="utf-8"?>

<window>	
	<background x="0" y="0" width="1024" height="768">
		<texture>ui\ui_static_mm_back_02</texture>
	</background>
	<main_dialog>
		<dialog x="233" y="157" width="548" height="461">
			<texture>ui_menu_options_dlg</texture>
		</dialog>
		<tab x="55" y="48" width="461" height="26">
			<button x="0" y="0" width="116" height="26">
				<texture_offset x="0" y="-7"/>
				<texture>ui_button_tablist</texture>
				<text font="normal" align="c">Video</text>
				<sound_t>weapons\generic_close</sound_t>					
			</button>
			<button x="116" y="0" width="116" height="26">
				<texture_offset x="0" y="-7"/>
				<texture>ui_button_tablist</texture>
				<text font="normal" align="c">Sound</text>
				<sound_t>weapons\generic_close</sound_t>
			</button>
			<button x="232" y="0" width="116" height="26">
				<texture_offset x="0" y="-7"/>
				<texture>ui_button_tablist</texture>
				<text font="normal" align="c">GamePlay</text>
				<sound_t>weapons\generic_close</sound_t>
			</button>
			<button x="348" y="0" width="116" height="26">
				<texture_offset x="0" y="-7"/>
				<texture>ui_button_tablist</texture>
				<text f6ont="normal" align="c">Controls</text>
				<sound_t>weapons\generic_close</sound_t>
			</button>
		</tab>
	</main_dialog>
	<tab_video>
		<cap_preset x="20" y="20" width="143" height="21">
			<text>Quality presets</text>
		</cap_preset>
		<cap_resolution x="20" y="45" width="143" height="21">
			<text>Resolution</text>
		</cap_resolution>
		<cap_gamma x="20" y="70" width="143" height="21">
			<text>Gamma</text>
		</cap_gamma>
		<cap_contrast x="20" y="95" width="143" height="21">
			<text>Contrast</text>
		</cap_contrast>
		<cap_brightness x="20" y="120" width="143" height="21">
			<text>Brightness</text>
		</cap_brightness>
		
		<check_fullscreen x="20" y="155" width="143" height="21">
			<options_item entry="rs_fullscreen" group="mm_opt_video"/>	
			<text>Full Screen</text>
		</check_fullscreen>
		<check_no_vsync x="20" y="180" width="143" height="21">
			<options_item entry="rs_no_v_sync" group="mm_opt_video"/>
			<text>no VSYNC</text>
		</check_no_vsync>
		
		<list_presets x="194" y="20" width="261" height="21">			
		</list_presets>
		<list_resolution x="194" y="45" width="261" height="21">
			<options_item entry="vid_mode" group="mm_opt_video"/>
		</list_resolution>
		
		<track_gamma x="194" y="70" width="261" height="21">
			<options_item entry="rs_c_gamma" group="mm_opt_video"/>
		</track_gamma>
		<track_contrast x="194" y="95" width="261" height="21">
			<options_item entry="rs_c_constrast" group="mm_opt_video"/>
		</track_contrast>
		<track_brightness x="194" y="120" width="261" height="21">
			<options_item entry="rs_c_brightness" group="mm_opt_video"/>
		</track_brightness>
	</tab_video>
	
	<frame x="0" y="0" width="470" height="330">
		<texture>ui_tablist_textbox</texture>		
	</frame>

</window>
